pyroscopegriddingcpu/__init__.py
pyroscopegriddingcpu/fileparser.py
pyroscopegriddingcpu/filter_data.py
pyroscopegriddingcpu/grid_ncf.py
pyroscopegriddingcpu/gridding.py
pyroscopegriddingcpu/gtools.py
pyroscopegriddingcpu/naming_conventions.py
pyroscopegriddingcpu/sat_data_input.py
pyroscopegriddingcpu/solar_zenith.py
pyroscopegriddingcpu/time_conv.py
pyroscopegriddingcpu-1.5.1.0.dist-info/LICENSE.txt
pyroscopegriddingcpu-1.5.1.0.dist-info/METADATA
pyroscopegriddingcpu-1.5.1.0.dist-info/WHEEL
pyroscopegriddingcpu-1.5.1.0.dist-info/entry_points.txt
pyroscopegriddingcpu-1.5.1.0.dist-info/top_level.txt
pyroscopegriddingcpu-1.5.1.0.dist-info/RECORD
