Metadata-Version: 2.2
Name: pyroscopegriddingcpu
Version: 1.5.1.0
Summary: Data fusion package for transforming L2 satellite to L3 spatial-temporal gridded data
Home-page: https://github.com/jwei-openscapes/aerosol-data-fusion
Author: Sally Zhao, Neil Gutkin
Author-email: zhaosally0@gmail.com
License: MIT
Keywords: data fusion,satellite,L2,L3
Classifier: Development Status :: 3 - Alpha
Classifier: Intended Audience :: Developers
Classifier: Topic :: Software Development :: Build Tools
Classifier: License :: OSI Approved :: MIT License
Classifier: Programming Language :: Python :: 3
Classifier: Programming Language :: Python :: 3.4
Classifier: Programming Language :: Python :: 3.5
Classifier: Programming Language :: Python :: 3.6
Classifier: Programming Language :: Python :: 3.7
Classifier: Programming Language :: Python :: 3.8
License-File: LICENSE.txt
Requires-Dist: pyhdf
Requires-Dist: numpy==1.23.5
Requires-Dist: joblib==1.2.0
Requires-Dist: netCDF4==1.6.3
Requires-Dist: pandas==2.0.0
Requires-Dist: pyyaml==6.0
Requires-Dist: argparse
Dynamic: author
Dynamic: author-email
Dynamic: classifier
Dynamic: description
Dynamic: description-content-type
Dynamic: home-page
Dynamic: keywords
Dynamic: license
Dynamic: requires-dist
Dynamic: summary
